elaina_segment-0.4.0.dist-info/RECORD
elaina_segment-0.4.0.dist-info/WHEEL
elaina_segment-0.4.0.dist-info/top_level.txt
elaina_segment-0.4.0.dist-info/METADATA
elaina_segment/segment_c.pyi
elaina_segment/__init__.py
elaina_segment/buffer_c.pyi
elaina_segment/segment_c.pxd
elaina_segment/segment_c.pyx
elaina_segment/segment_py.py
elaina_segment/buffer.py
elaina_segment/segment_c.cpython-311-darwin.so
elaina_segment/segment.py
elaina_segment/err.py
elaina_segment/buffer_c.pyx
elaina_segment/buffer_c.cpython-311-darwin.so
elaina_segment/const.py
elaina_segment/buffer_py.py
