Metadata-Version: 2.1
Name: elaina-segment
Version: 0.4.0
Summary: Default template for PDM package
Author-email: Elaina <GreyElaina@outlook.com>
License: MIT
Requires-Python: >=3.9
